aiokem/__init__.py
aiokem/exceptions.py
aiokem/helpers.py
aiokem/main.py
aiokem/message_logger.py
aiokem-1.1.4.dist-info/licenses/LICENSE
aiokem-1.1.4.dist-info/METADATA
aiokem-1.1.4.dist-info/WHEEL
aiokem-1.1.4.dist-info/top_level.txt
aiokem-1.1.4.dist-info/RECORD
