Metadata-Version: 2.4
Name: aiokem
Version: 1.1.4
Summary: Async API for Kohler Energy Management
Author: Pete Sage
Author-email: "J. Nick Koston" <nick@koston.org>
License: MIT
Project-URL: Bug Tracker, https://github.com/kohlerlibs/aiokem/issues
Project-URL: Changelog, https://github.com/kohlerlibs/aiokem/blob/main/CHANGELOG.md
Project-URL: documentation, https://aiokem.readthedocs.io
Project-URL: repository, https://github.com/kohlerlibs/aiokem
Classifier: Development Status :: 2 - Pre-Alpha
Classifier: Intended Audience :: Developers
Classifier: Natural Language :: English
Classifier: Operating System :: OS Independent
Classifier: Programming Language :: Python :: 3.12
Classifier: Programming Language :: Python :: 3.13
Classifier: Topic :: Software Development :: Libraries
Requires-Python: >=3.12
License-File: LICENSE
Requires-Dist: aiohttp>=3.11
Requires-Dist: pyjwt>=2.10.1
Dynamic: license-file
